Ciola/__init__.py
Ciola/cords.py
Ciola/email_gen.py
Ciola/humanbehavior.py
Ciola/password_gen.py
Ciola/random_user_agent.py
Ciola/wifi_password.py
Ciola/windows_mail.py
Ciola-1.0.6.dist-info/LICENSE.txt
Ciola-1.0.6.dist-info/METADATA
Ciola-1.0.6.dist-info/WHEEL
Ciola-1.0.6.dist-info/top_level.txt
Ciola-1.0.6.dist-info/RECORD
