Metadata-Version: 2.1
Name: Ciola
Version: 1.0.6
Summary: A personal library
Author: Lapsus
Author-email: 
Classifier: Programming Language :: Python :: 3.10
Classifier: License :: OSI Approved :: MIT License
Classifier: Operating System :: OS Independent
Requires-Python: >=3.10
License-File: LICENSE.txt
Requires-Dist: pyautogui
